searchphrase.py
functest_plearner-1.0.dist-info/METADATA
functest_plearner-1.0.dist-info/WHEEL
functest_plearner-1.0.dist-info/top_level.txt
functest_plearner-1.0.dist-info/RECORD
