Metadata-Version: 2.1
Name: functest-plearner
Version: 1.0
Summary: sdfsa
Home-page: UNKNOWN
Author: piy
Author-email: 
License: UNKNOWN
Platform: UNKNOWN
